authware/__init__.py
authware/application.py
authware/cryptography.py
authware/exceptions.py
authware/hwid.py
authware/user.py
authware/utils.py
authware_sync-1.0.0.dist-info/LICENSE
authware_sync-1.0.0.dist-info/METADATA
authware_sync-1.0.0.dist-info/WHEEL
authware_sync-1.0.0.dist-info/top_level.txt
authware_sync-1.0.0.dist-info/RECORD
