Metadata-Version: 2.1
Name: authware-sync
Version: 1.0.0
Summary: Synchronous wrapper for Authware in Python 3.5+
Home-page: https://github.com/AuthwareCloud/python-sync-sdk
Author: Authware
Author-email: support@authware.org
License: UNKNOWN
Project-URL: Bug Tracker, https://github.com/AuthwareCloud/python-sync-sdk/issues
Platform: UNKNOWN
Classifier: Programming Language :: Python :: 3
Classifier: License :: OSI Approved :: MIT License
Classifier: Operating System :: OS Independent
Requires-Python: >=3.5
License-File: LICENSE
